tui_rvds/__init__.py
tui_rvds/uebung3.py
tui_rvds/pandas/__init__.py
tui_rvds/pandas/tests.py
tui_rvds/python/__init__.py
tui_rvds/python/flow/__init__.py
tui_rvds/python/flow/tests.py
tui_rvds/python/fun/__init__.py
tui_rvds/python/fun/tests.py
tui_rvds/python/loops/__init__.py
tui_rvds/python/loops/tests.py
tui_rvds/python/vad/__init__.py
tui_rvds/python/vad/tests.py
tui_rvds-2025.8.14.dist-info/METADATA
tui_rvds-2025.8.14.dist-info/WHEEL
tui_rvds-2025.8.14.dist-info/top_level.txt
tui_rvds-2025.8.14.dist-info/RECORD
