Metadata-Version: 2.4
Name: tui_rvds
Version: 2025.8.14
Summary: everything you need for our jupyter notebooks
Home-page: https://dbgit.prakinf.tu-ilmenau.de/lectures/ringvorlesung-data-science
Author: Eric Tröbs
Author-email: eric.troebs@tu-ilmenau.de
Requires-Python: >=3.12
Requires-Dist: jupyter
Requires-Dist: checkmarkandcross
Requires-Dist: matplotlib==3.10.3
Requires-Dist: numpy==2.3.0
Requires-Dist: pandas==2.3.0
Requires-Dist: plotly==6.1.2
Requires-Dist: pyreadstat==1.2.9
Dynamic: author
Dynamic: author-email
Dynamic: description
Dynamic: description-content-type
Dynamic: home-page
Dynamic: requires-dist
Dynamic: requires-python
Dynamic: summary
